viapy/__init__.py
viapy/api.py
viapy/test_urls.py
viapy/urls.py
viapy/views.py
viapy/widgets.py
viapy/tests/test_api.py
viapy/tests/test_django.py
viapy/tests/fixtures/102333412_rdf.xml
viapy/tests/fixtures/sru_search.json
viapy-0.4.0.dist-info/METADATA
viapy-0.4.0.dist-info/WHEEL
viapy-0.4.0.dist-info/licenses/LICENSE
viapy-0.4.0.dist-info/RECORD
