Metadata-Version: 2.4
Name: viapy
Version: 0.4.0
Summary: Python module for interacting with VIAF data & APIs
Project-URL: Repository, https://github.com/Princeton-CDH/viapy
Project-URL: Changelog, https://github.com/Princeton-CDH/viapy/blob/main/CHANGELOG.rst
Author-email: Center for Digital Humanities at Princeton <cdh@princeton.edu>
License: Apache-2
License-File: LICENSE
Classifier: Environment :: Web Environment
Classifier: Framework :: Django
Classifier: Framework :: Django :: 3.2
Classifier: Framework :: Django :: 4.0
Classifier: Framework :: Django :: 4.1
Classifier: Framework :: Django :: 4.2
Classifier: Framework :: Django :: 5.0
Classifier: Intended Audience :: Developers
Classifier: License :: OSI Approved :: Apache Software License
Classifier: Operating System :: OS Independent
Classifier: Programming Language :: Python
Classifier: Programming Language :: Python :: 3
Classifier: Programming Language :: Python :: 3.9
Classifier: Programming Language :: Python :: 3.10
Classifier: Programming Language :: Python :: 3.11
Classifier: Programming Language :: Python :: 3.12
Classifier: Topic :: Internet :: WWW/HTTP
Classifier: Topic :: Software Development :: Libraries :: Python Modules
Requires-Python: >=3.9
Requires-Dist: attrdict3
Requires-Dist: cached-property
Requires-Dist: rdflib
Requires-Dist: requests
Provides-Extra: dev
Requires-Dist: django-autocomplete-light; extra == 'dev'
Requires-Dist: django>=3.2; extra == 'dev'
Requires-Dist: pre-commit; extra == 'dev'
Requires-Dist: pytest; extra == 'dev'
Requires-Dist: pytest-cov; extra == 'dev'
Requires-Dist: pytest-django; extra == 'dev'
Requires-Dist: sphinx; extra == 'dev'
Provides-Extra: django
Requires-Dist: django-autocomplete-light; extra == 'django'
Requires-Dist: django>=3.2; extra == 'django'
Provides-Extra: django-test
Requires-Dist: django-autocomplete-light; extra == 'django-test'
Requires-Dist: django>=3.2; extra == 'django-test'
Requires-Dist: pytest-django; extra == 'django-test'
Provides-Extra: docs
Requires-Dist: sphinx; extra == 'docs'
Provides-Extra: test
Requires-Dist: pytest; extra == 'test'
Requires-Dist: pytest-cov; extra == 'test'
Provides-Extra: test-all
Requires-Dist: django-autocomplete-light; extra == 'test-all'
Requires-Dist: django>=3.2; extra == 'test-all'
Requires-Dist: pytest; extra == 'test-all'
Requires-Dist: pytest-cov; extra == 'test-all'
Requires-Dist: pytest-django; extra == 'test-all'
